lazex.py
lazex-0.4.1.dist-info/WHEEL
lazex-0.4.1.dist-info/METADATA
lazex-0.4.1.dist-info/RECORD
