Metadata-Version: 2.1
Name: lazex
Version: 0.4.1
Summary: Allow functions to examine and modify the AST of their arguments
Home-page: https://github.com/L3viathan/lazex
Author: L3viathan
Author-email: git@l3vi.de
Requires-Python: >=3.8,<4.0
Classifier: Programming Language :: Python :: 3
Classifier: Programming Language :: Python :: 3.10
Classifier: Programming Language :: Python :: 3.8
Classifier: Programming Language :: Python :: 3.9
Requires-Dist: astunparse (>=1.6.3,<2.0.0)
Project-URL: Repository, https://github.com/L3viathan/lazex
